qmatch/__init__.py
qmatch/_match_fast_.py
qmatch/_match_simple_.py
qmatch/_match_triang_.py
qmatch/_mean_offset_.py
qmatch/match_fast.py
qmatch/match_simple.py
qmatch/match_triang.py
qmatch-0.20.dist-info/LICENSE
qmatch-0.20.dist-info/METADATA
qmatch-0.20.dist-info/WHEEL
qmatch-0.20.dist-info/top_level.txt
qmatch-0.20.dist-info/RECORD
