Metadata-Version: 2.1
Name: qmatch
Version: 0.20
Summary: Some astronomical matching functions.
Home-page: https://gitee.com/drjiezheng/qmatch
Author: Dr Jie Zheng
Author-email: jiezheng@nao.cas.cn
License: MIT
Classifier: Development Status :: 5 - Production/Stable
Classifier: Intended Audience :: Science/Research
Classifier: License :: OSI Approved :: MIT License
Classifier: Operating System :: OS Independent
Classifier: Programming Language :: Python :: 3.7
Classifier: Topic :: Scientific/Engineering :: Physics
Classifier: Topic :: Scientific/Engineering :: Astronomy
Requires: numpy
Requires: scipy
Requires: astropy
License-File: LICENSE
